{
  "taskPreset": [
    {
      "id": "filter-1",
      "label": "All Priority / All Status",
      "ownerId": null,
      "clinicWide": true,
      "_tenant": "",
      "order": 1,
      "selections": {
        "priority": {
          "query": [
            "",
            "p1",
            "p2",
            "p3"
          ]
        },
        "status": {
          "query": [
            "",
            "complete",
            "in-progress",
            "not-started"
          ]
        }
      }
    },
    {
      "id": "filter-2",
      "label": "Doc Review / Assessments",
      "ownerId": null,
      "clinicWide": true,
      "_tenant": "",
      "order": 2,
      "selections": {
        "status": {
          "query": [
            "",
            "in-progress",
            "not-started"
          ]
        },
        "tags": {
          "query": [
            "assessments",
            "doc review"
          ]
        }
      }
    },
    {
      "id": "filter-3",
      "label": "My Custom Filter",
      "ownerId": "616620c0df1f010009ea4a94",
      "clinicWide": false,
      "_tenant": "",
      "order": 3,
      "selections": {
        "priority": {
          "query": [
            "p1",
            "p2",
            "p3"
          ]
        },
        "ownerId": {
          "query": [
            "616620c0df1f010009ea4a94"
          ]
        },
        "status": {
          "query": [
            "",
            "in-progress",
            "not-started"
          ]
        }
      }
    },
    {
      "id": "filter-4",
      "label": "Ramily",
      "ownerId": "616620c0df1f010009ea4a94",
      "clinicWide": false,
      "_tenant": "",
      "order": 4,
      "selections": {
        "priority": {
          "query": [
            "p1"
          ]
        },
        "ownerId": {
          "query": [
            "5d50e5cd3560d100085664e7",
            "605a7556adb81500075b0de8",
            "616620c0df1f010009ea4a94",
            "61dc7338a3e8fb00093c6ed3"
          ]
        },
        "status": {
          "query": [
            "complete"
          ]
        },
        "tags": {
          "query": [
            "health maintenance"
          ]
        }
      }
    },
    {
      "id": "filter-5",
      "label": "My Tasks",
      "ownerId": "616620c0df1f010009ea4a94",
      "clinicWide": false,
      "_tenant": "",
      "order": 5,
      "selections": {
        "priority": {
          "query": [
            "",
            "p1",
            "p2",
            "p3"
          ]
        },
        "ownerId": {
          "query": [
            "616620c0df1f010009ea4a94"
          ]
        },
        "status": {
          "query": [
            "",
            "complete",
            "in-progress",
            "not-started"
          ]
        },
        "tags": {
          "query": [
            "assessments",
            "doc review",
            "test"
          ]
        }
      }
    }
  ]
}